adi_distributions/Binomialdistribution.py
adi_distributions/Gaussiandistribution.py
adi_distributions/Generaldistribution.py
adi_distributions/__init__.py
adithya_distributions/Binomialdistribution.py
adithya_distributions/Gaussiandistribution.py
adithya_distributions/Generaldistribution.py
adithya_distributions/__init__.py
adithya_distributions-1.0.dist-info/METADATA
adithya_distributions-1.0.dist-info/WHEEL
adithya_distributions-1.0.dist-info/top_level.txt
adithya_distributions-1.0.dist-info/RECORD
