Metadata-Version: 2.1
Name: adithya_distributions
Version: 1.0
Summary: Gaussian and Binomial distributions
Author: Adithya Chintala
